<?xml version='1.0' encoding='UTF-8'?>

<!--+
    |     Copyright European Community 2006 - Licensed under the EUPL V.1.0
    |
    |  		   http://ec.europa.eu/idabc/en/document/6523
    |
    +-->

<!DOCTYPE beans PUBLIC '-//SPRING//DTD BEAN//EN' 'http://www.springframework.org/dtd/spring-beans.dtd'>

<beans>

  <!-- Task scheduler -->
  <!-- Alfresco Triggers should not appear here - the scheduler should be injected into the trigger definition -->
  <!-- This bean should not need to apear else where in extension configuration -->
  <bean id="schedulerFactory" class="org.springframework.scheduling.quartz.SchedulerFactoryBean">
      <!-- Property to allow Jobs to be viewed and managed in Javamelody -->
   	  <property name="exposeSchedulerInRepository" value="true" />
      <property name="waitForJobsToCompleteOnShutdown">
          <value>true</value>
      </property>
      <property name="configLocation">
          <value>classpath:alfresco/extension/domain/quartz.properties</value>
      </property>
      <property name="schedulerName">
          <value>DefaultScheduler</value>
      </property>
      <!-- Do not auto start the scheduler - this is done at the end of the bootstrap process -->
      <property name="autoStartup">
          <value>false</value>
      </property>

  </bean>



<!--
	"0 0 12 * * ?"  	  	Fire at 12pm (noon) every day
	"0 15 10 ? * *"  	  	Fire at 10:15am every day
	"0 15 10 * * ?" 	  	Fire at 10:15am every day
	"0 15 10 * * ? *" 	  	Fire at 10:15am every day
	"0 15 10 * * ? 2005" 	  	Fire at 10:15am every day during the year 2005
	"0 * 14 * * ?" 	  	Fire every minute starting at 2pm and ending at 2:59pm, every day
	"0 0/5 14 * * ?" 	  	Fire every 5 minutes starting at 2pm and ending at 2:55pm, every day
	"0 0/5 14,18 * * ?" 	  	Fire every 5 minutes starting at 2pm and ending at 2:55pm, AND fire every 5 minutes starting at 6pm and ending at 6:55pm, every day
	"0 0-5 14 * * ?" 	  	Fire every minute starting at 2pm and ending at 2:05pm, every day
	"0 10,44 14 ? 3 WED" 	  	Fire at 2:10pm and at 2:44pm every Wednesday in the month of March.
	"0 15 10 ? * MON-FRI" 	  	Fire at 10:15am every Monday, Tuesday, Wednesday, Thursday and Friday
	"0 15 10 15 * ?" 	  	Fire at 10:15am on the 15th day of every month
	"0 15 10 L * ?" 	  	Fire at 10:15am on the last day of every month
	"0 15 10 ? * 6L" 	  	Fire at 10:15am on the last Friday of every month
	"0 15 10 ? * 6L" 	  	Fire at 10:15am on the last Friday of every month
	"0 15 10 ? * 6L 2002-2005" 	  	Fire at 10:15am on every last friday of every month during the years 2002, 2003, 2004 and 2005
	"0 15 10 ? * 6#3" 	  	Fire at 10:15am on the third Friday of every month
-->

	<bean id="emailListenersTrigger" class="org.alfresco.util.TriggerBean">
		<property name="jobDetail">
			<bean id="emailListenersJobDetail" class="org.springframework.scheduling.quartz.JobDetailBean">
				<property name="jobClass">
					<value>eu.cec.digit.circabc.service.event.MeetingResponseListener</value>
				</property>
				<property name="jobDataAsMap">
					<map>
						<entry key="serviceRegistry">
							<ref bean="ServiceRegistry" />
						</entry>
						<entry key="circabcServiceRegistry">
							<ref bean="circabcServiceRegistry" />
						</entry>
					</map>
				</property>
			</bean>
		</property>
		<property name="startDelay">
			<value>60000</value>
		</property>
		<property name="repeatInterval">
			<value>300000</value>
		</property>
		<property name="scheduler">
			<ref bean="schedulerFactory" />
		</property>
	</bean>

    <bean id="plannedGlobalStatisticsTrigger" class="org.alfresco.util.CronTriggerBean">
		<property name="jobDetail">
			<bean id="plannedGlobalStatisticsJobDetail" class="org.springframework.scheduling.quartz.JobDetailBean">
				<property name="jobClass">
					<value>eu.cec.digit.circabc.service.statistics.global.GlobalStatisticsJobListener</value>
				</property>
				<property name="jobDataAsMap">
					<map>
						<entry key="globalStatisticsService">
							<ref bean="GlobalStatisticsService" />
						</entry>
						<entry key="circabcLockService">
							<ref bean="CircabcLockService" />
						</entry>
						<entry key="enabledOnHostname" value="${circabc.global.statistics.enabled.on.hostname}" />
					</map>
				</property>
			</bean>
		</property>
		<property name="cronExpression">
<!-- 		 <value>0 0/1 * * * ?</value> -->
		 <value>0 5 0 * * ?</value>
        </property>
		<property name="scheduler">
			<ref bean="schedulerFactory" />
		</property>
		<property name="enabled">
			<value>${circabc.global.statistics.enabled}</value>
		</property>
	</bean>
	
	<bean id="autoUploadFtpTrigger" class="org.alfresco.util.CronTriggerBean">
		<property name="jobDetail">
			<bean id="autoUploadFtpJobDetail" class="org.springframework.scheduling.quartz.JobDetailBean">
				<property name="jobClass">
					<value>eu.cec.digit.circabc.service.config.auto.upload.AutoUploadJobListener</value>
				</property>
				<property name="jobDataAsMap">
					<map>
						<entry key="autoUploadManagementService">
							<ref bean="AutoUploadManagementService" />
						</entry>
						<entry key="enabledOnHostname" value="${app.autoupload.enabled.on.hostname}" />
					</map>
				</property>
			</bean>
		</property>
		<property name="cronExpression">
<!-- 		 <value>0 0/1 * * * ?</value> -->
            <value>0 0 */1 * * ?</value>
        </property>
		<property name="scheduler">
			<ref bean="schedulerFactory" />
		</property>
		<property name="enabled">
			<value>${app.autoupload.enabled}</value>
		</property>
	</bean>
	<!--
	Cron that checking machine translations
	and update repository
-->
  <bean id="machineTranslationTrigger" class="org.alfresco.util.TriggerBean">
		<property name="jobDetail">
			<bean id="machineTranslationJobDetail" class="org.springframework.scheduling.quartz.JobDetailBean">
				<property name="jobClass">
					<value>eu.cec.digit.circabc.repo.translation.MachineTranslationJob</value>
				</property>
				<property name="jobDataAsMap">
					<map>
						<entry key="serviceRegistry">
							<ref bean="ServiceRegistry" />
						</entry>
						<entry key="circabcServiceRegistry">
							<ref bean="circabcServiceRegistry" />
						</entry>
					</map>
				</property>
			</bean>
		</property>
		<property name="startDelay">
			<value>90000</value>
		</property>
		<property name="repeatInterval">
			<value>18000</value>
		</property>
		<property name="scheduler">
			<ref bean="schedulerFactory" />
		</property>
	</bean>
	
	<!-- Job that pre-renders the PDF documents for the document preview -->
	<!-- Batch of 50 documents -->
	<!-- Start after 1 minute -->
	<!-- Restart after 2 hours -->
	<bean id="previewPDFRenditionTrigger" class="org.alfresco.util.TriggerBean">
		<property name="jobDetail">
			<bean id="previewPDFRenditionJobDetail" class="org.springframework.scheduling.quartz.JobDetailBean">
				<property name="jobClass">
					<value>eu.cec.digit.circabc.service.rendition.job.PreviewPDFRenditionJob</value>
				</property>
				<property name="jobDataAsMap">
					<map>
						<entry key="serviceRegistry">
							<ref bean="ServiceRegistry" />
						</entry>
						<entry key="circabcServiceRegistry">
							<ref bean="circabcServiceRegistry" />
						</entry>
						<entry key="renditionServiceConfig">
							<ref bean="renditionServiceConfig" />
						</entry>
						<entry key="renderAmount" value="50" />
						<entry key="startYear" value="2014" />
					</map>
				</property>
			</bean>
		</property>
		<property name="startDelay">
			<value>60000</value>
		</property>
		<property name="repeatInterval">
			<value>7200000</value>
		</property>
		<property name="scheduler">
			<ref bean="schedulerFactory" />
		</property>
	</bean>
	
	<bean id="renderTrigger" class="org.alfresco.util.TriggerBean">
		<property name="jobDetail">
			<bean id="renderJobDetail" class="org.springframework.scheduling.quartz.JobDetailBean">
				<property name="jobClass">
					<value>eu.cec.digit.circabc.service.rendition.job.RenderJob</value>
				</property>
				<property name="jobDataAsMap">
					<map>
						<entry key="serviceRegistry">
							<ref bean="ServiceRegistry" />
						</entry>
						<entry key="circabcServiceRegistry">
							<ref bean="circabcServiceRegistry" />
						</entry>
						<entry key="renditionServiceConfig">
							<ref bean="renditionServiceConfig" />
						</entry>
						<entry key="circabcLockService">
							<ref bean="CircabcLockService" />
						</entry>
					</map>
				</property>
			</bean>
		</property>
		<property name="startDelay">
			<value>60000</value>
		</property>
		<property name="repeatInterval">
			<value>120000</value>
		</property>
		<property name="scheduler">
			<ref bean="schedulerFactory" />
		</property>
		<property name="enabled">
			<value>${preview.render.job.enabled}</value>
		</property>
	</bean>

<!--
	Cron that checking machine translations
	and update repository
-->
  <bean id="machineTranslationCleanTrigger" class="org.alfresco.util.CronTriggerBean">
		<property name="jobDetail">
			<bean id="machineTranslationCleanJobDetail" class="org.springframework.scheduling.quartz.JobDetailBean">
				<property name="jobClass">
					<value>eu.cec.digit.circabc.repo.translation.MachineTranslationCleanJob</value>
				</property>
				<property name="jobDataAsMap">
					<map>
						<entry key="serviceRegistry">
							<ref bean="ServiceRegistry" />
						</entry>
						<entry key="circabcServiceRegistry">
							<ref bean="circabcServiceRegistry" />
						</entry>
					</map>
				</property>
			</bean>
		</property>
		<property name="cronExpression">
			<!--  each first in each month at 19:30 -->
            <value>0 30 19 1 1-12 ?</value>
        </property>
		<property name="scheduler">
			<ref bean="schedulerFactory" />
		</property>
	</bean>


<bean id="ldapSyncJobTrigger" class="org.alfresco.util.CronTriggerBean">
		<property name="jobDetail">
			<bean id="ldapSyncJobDetail" class="org.springframework.scheduling.quartz.JobDetailBean">
				<property name="jobClass">
					<value>eu.cec.digit.circabc.repo.user.LdapSyncJob</value>
				</property>
				<property name="jobDataAsMap">
					<map>
						<entry key="serviceRegistry">
							<ref bean="ServiceRegistry" />
						</entry>
						<entry key="circabcServiceRegistry">
							<ref bean="circabcServiceRegistry" />
						</entry>
						<entry key="excludedUsers">
							<list>
								<value>admin</value>
								<value>guest</value>
								<value>mtuser</value>
								<value>&lt;USERNAME&gt;</value>
								<value>sanco_sps</value>
								<value>echadcuser</value> 
							</list>
						</entry>
					</map>
				</property>
			</bean>
		</property>
		<property name="cronExpression">
            <value>${ldap.sync.job.cron.expression}</value>
        </property>
		<property name="scheduler">
			<ref bean="schedulerFactory" />
		</property>
	</bean>
	<bean id="logJobTrigger" class="org.alfresco.util.TriggerBean">
		<property name="jobDetail">
			<bean id="logJobDetail" class="org.springframework.scheduling.quartz.JobDetailBean">
				<property name="jobClass">
					<value>eu.cec.digit.circabc.repo.log.LogJob</value>
				</property>
				<property name="jobDataAsMap">
					<map>
						<entry key="serviceRegistry">
							<ref bean="ServiceRegistry" />
						</entry>
						<entry key="circabcServiceRegistry">
							<ref bean="circabcServiceRegistry" />
						</entry>
					</map>
				</property>
			</bean>
		</property>
		<property name="startDelay">
			<value>90000</value>
		</property>
		<property name="repeatInterval">
			<value>18000</value>
		</property>
		<property name="scheduler">
			<ref bean="schedulerFactory" />
		</property>
	</bean>

	<bean id="unlockJobTrigger" class="org.alfresco.util.TriggerBean">
		<property name="jobDetail">
			<bean id="unlockJobDetail" class="org.springframework.scheduling.quartz.JobDetailBean">
				<property name="jobClass">
					<value>eu.cec.digit.circabc.repo.lock.UnlockJob</value>
				</property>
				<property name="jobDataAsMap">
					<map>
						<entry key="serviceRegistry">
							<ref bean="ServiceRegistry" />
						</entry>
						<entry key="circabcServiceRegistry">
							<ref bean="circabcServiceRegistry" />
						</entry>
						<entry key="maxJobLockTimeInHours">
							<value>${max.job.lock.time.in.hours}</value>
						</entry>
					</map>
				</property>
			</bean>
		</property>
		<property name="startDelay">
			<value>3600000</value>
		</property>
		<property name="repeatInterval">
			<value>3600000</value>
		</property>
		<property name="scheduler">
			<ref bean="schedulerFactory" />
		</property>
	</bean>

	<bean id="aresBridgeJobTrigger" class="org.alfresco.util.TriggerBean">
		<property name="jobDetail">
			<bean id="aresBridgeDetail" class="org.springframework.scheduling.quartz.JobDetailBean">
				<property name="jobClass">
					<value>eu.cec.digit.circabc.repo.ares.AresBridgeJob</value>
				</property>
				<property name="jobDataAsMap">
					<map>
						<entry key="serviceRegistry">
							<ref bean="ServiceRegistry" />
						</entry>
						<entry key="circabcServiceRegistry">
							<ref bean="circabcServiceRegistry" />
						</entry>
					</map>
				</property>
			</bean>
		</property>
		<property name="startDelay">
			<value>90000</value>
		</property>
		<property name="repeatInterval">
			<value>18000</value>
		</property>
		<property name="scheduler">
			<ref bean="schedulerFactory" />
		</property>
	</bean>
	
	<bean id="revocationTrigger" class="org.alfresco.util.CronTriggerBean">
		<property name="jobDetail">
			<bean id="revocationJobDetail" class="org.springframework.scheduling.quartz.JobDetailBean">
				<property name="jobClass">
					<value>eu.cec.digit.circabc.service.revocation.job.RevocationJob</value>
				</property>
				<property name="jobDataAsMap">
					<map>
						<entry key="nodeService">
							<ref bean="nodeService" />
						</entry>
						<entry key="personService">
							<ref bean="personService" />
						</entry>
						<entry key="groupsApi">
							<ref bean="groupsApi" />
						</entry>
						<entry key="usersApi">
							<ref bean="usersApi" />
						</entry>
						<entry key="historyApi">
							<ref bean="historyApi" />
						</entry>
						<entry key="transactionService">
							<ref bean="transactionService" />
						</entry>
						<entry key="lockService">
							<ref bean="circabcLockService" />
						</entry>
					</map>
				</property>
			</bean>
		</property>
		<property name="cronExpression">
            <value>0 0 */1 * * ?</value>
        </property>
		<property name="scheduler">
			<ref bean="schedulerFactory" />
		</property>
		<property name="enabled">
			<value>${revocation.job.enabled}</value>
		</property>
	</bean>
	
	<bean id="cleanGroupPermissionTrigger" class="org.alfresco.util.CronTriggerBean">
		<property name="jobDetail">
			<bean id="cleanGroupPermissionJobDetail" class="org.springframework.scheduling.quartz.JobDetailBean">
				<property name="jobClass">
					<value>eu.cec.digit.circabc.service.revocation.job.CleanGroupPermissionJob</value>
				</property>
				<property name="jobDataAsMap">
					<map>
						<entry key="nodeService">
							<ref bean="nodeService" />
						</entry>
						<entry key="personService">
							<ref bean="personService" />
						</entry>
						<entry key="groupsApi">
							<ref bean="groupsApi" />
						</entry>
						<entry key="usersApi">
							<ref bean="usersApi" />
						</entry>
						<entry key="historyApi">
							<ref bean="historyApi" />
						</entry>
						<entry key="transactionService">
							<ref bean="transactionService" />
						</entry>
						<entry key="lockService">
							<ref bean="circabcLockService" />
						</entry>
					</map>
				</property>
			</bean>
		</property>
		<property name="cronExpression">
            <value>0 */5 * * * ?</value>
        </property>
		<property name="scheduler">
			<ref bean="schedulerFactory" />
		</property>
		<property name="enabled">
			<value>${clean.permission.job.enabled}</value>
		</property>
	</bean>

	<bean id="memberExpirationTrigger" class="org.alfresco.util.CronTriggerBean">
		<property name="jobDetail">
			<bean id="memberExpirationJobDetail" class="org.springframework.scheduling.quartz.JobDetailBean">
				<property name="jobClass">
					<value>eu.cec.digit.circabc.service.member.ExpiredMembersJob</value>
				</property>
				<property name="jobDataAsMap">
					<map>
						<entry key="groupsApi">
							<ref bean="groupsApi" />
						</entry>
						<entry key="historyApi">
							<ref bean="historyApi" />
						</entry>
						<entry key="lockService">
							<ref bean="circabcLockService" />
						</entry>
					</map>
				</property>
			</bean>
		</property>
		<property name="cronExpression">
            <value>0 */5 * * * ?</value>
        </property>
		<property name="scheduler">
			<ref bean="schedulerFactory" />
		</property>
		<property name="enabled">
			<value>true</value>
		</property>
	</bean>
	
	<bean id="distributionListSenderTrigger" class="org.alfresco.util.CronTriggerBean">
		<property name="jobDetail">
			<bean id="distributionListSenderJobDetail" class="org.springframework.scheduling.quartz.JobDetailBean">
				<property name="jobClass">
					<value>eu.cec.digit.circabc.service.app.DistributionListSenderJob</value>
				</property>
				<property name="jobDataAsMap">
					<map>
						<entry key="appMessageApi">
							<ref bean="appMessageApi" />
						</entry>
						<entry key="notificationService">
							<ref bean="circabcNotificationService" />
						</entry>
						<entry key="lockService">
							<ref bean="circabcLockService" />
						</entry>
					</map>
				</property>
			</bean>
		</property>
		<property name="cronExpression">
            <value>0 0 0 ? * MON *</value>
        </property>
		<property name="scheduler">
			<ref bean="schedulerFactory" />
		</property>
		<property name="enabled">
			<value>${distribution.list.sender.job.enabled}</value>
		</property>
	</bean>
</beans>
